LICENSE
MANIFEST.in
README.md
requirements.txt
setup.py
iraclis/__author__.txt
iraclis/__author_email__.txt
iraclis/__databases__.pickle
iraclis/__databases__.py
iraclis/__description__.txt
iraclis/__init__.py
iraclis/__main__.py
iraclis/__url__.txt
iraclis/__version__.txt
iraclis/classes.py
iraclis/errors.py
iraclis/images1_reduction.py
iraclis/images2_calibration.py
iraclis/images3_photometry.py
iraclis/lightcurves1_fitting.py
iraclis/pipeline.py
iraclis.egg-info/PKG-INFO
iraclis.egg-info/SOURCES.txt
iraclis.egg-info/dependency_links.txt
iraclis.egg-info/entry_points.txt
iraclis.egg-info/not-zip-safe
iraclis.egg-info/requires.txt
iraclis.egg-info/top_level.txt